{".class":"MypyFile","_fullname":"onnx.reference.ops.op_lstm","future_import_flags":["annotations"],"is_partial_stub_package":false,"is_stub":false,"names":{".class":"SymbolTable","CommonLSTM":{".class":"SymbolTableNode","kind":"Gdef","node":{".class":"TypeInfo","_promote":[],"abstract_attributes":[],"alt_promote":null,"bases":["onnx.reference.op_run.OpRun"],"dataclass_transform_spec":null,"declared_metaclass":null,"defn":{".class":"ClassDef","fullname":"onnx.reference.ops.op_lstm.CommonLSTM","name":"CommonLSTM","type_vars":[]},"deletable_attributes":[],"deprecated":null,"flags":[],"fullname":"onnx.reference.ops.op_lstm.CommonLSTM","has_param_spec_type":false,"metaclass_type":"abc.ABCMeta","metadata":{},"module_name":"onnx.reference.ops.op_lstm","mro":["onnx.reference.ops.op_lstm.CommonLSTM","onnx.reference.op_run.OpRun","abc.ABC","builtins.object"],"names":{".class":"SymbolTable","__init__":{".class":"SymbolTableNode","kind":"Mdef","node":{".class":"FuncDef","abstract_status":0,"arg_kinds":[0,0,0],"arg_names":["self","onnx_node","run_params"],"dataclass_transform_spec":null,"deprecated":null,"flags":[],"fullname":"onnx.reference.ops.op_lstm.CommonLSTM.__init__","name":"__init__","type":null}},"_run":{".class":"SymbolTableNode","kind":"Mdef","node":{".class":"FuncDef","abstract_status":0,"arg_kinds":[0,0,0,0,1,1,1,1,1,1,1,1,1,1,1,1,1],"arg_names":["self","X","W","R","B","sequence_lens","initial_h","initial_c","P","activation_alpha","activation_beta","activations","clip","direction","hidden_size","input_forget","layout"],"dataclass_transform_spec":null,"deprecated":null,"flags":[],"fullname":"onnx.reference.ops.op_lstm.CommonLSTM._run","name":"_run","type":null}},"_step":{".class":"SymbolTableNode","kind":"Mdef","node":{".class":"FuncDef","abstract_status":0,"arg_kinds":[0,0,0,0,0,0,0,0,0],"arg_names":["self","X","R","B","W","H_0","C_0","P","num_directions"],"dataclass_transform_spec":null,"deprecated":null,"flags":[],"fullname":"onnx.reference.ops.op_lstm.CommonLSTM._step","name":"_step","type":{".class":"CallableType","arg_kinds":[0,0,0,0,0,0,0,0,0],"arg_names":["self","X","R","B","W","H_0","C_0","P","num_directions"],"arg_types":["onnx.reference.ops.op_lstm.CommonLSTM",{".class":"Instance","args":[{".class":"Instance","args":[{".class":"AnyType","missing_import_name":null,"source_any":null,"type_of_any":6}],"extra_attrs":null,"type_ref":"builtins.tuple"},{".class":"Instance","args":[{".class":"AnyType","missing_import_name":null,"source_any":null,"type_of_any":2}],"extra_attrs":null,"type_ref":"numpy.dtype"}],"extra_attrs":null,"type_ref":"numpy.ndarray"},{".class":"Instance","args":[{".class":"Instance","args":[{".class":"AnyType","missing_import_name":null,"source_any":null,"type_of_any":6}],"extra_attrs":null,"type_ref":"builtins.tuple"},{".class":"Instance","args":[{".class":"AnyType","missing_import_name":null,"source_any":null,"type_of_any":2}],"extra_attrs":null,"type_ref":"numpy.dtype"}],"extra_attrs":null,"type_ref":"numpy.ndarray"},{".class":"Instance","args":[{".class":"Instance","args":[{".class":"AnyType","missing_import_name":null,"source_any":null,"type_of_any":6}],"extra_attrs":null,"type_ref":"builtins.tuple"},{".class":"Instance","args":[{".class":"AnyType","missing_import_name":null,"source_any":null,"type_of_any":2}],"extra_attrs":null,"type_ref":"numpy.dtype"}],"extra_attrs":null,"type_ref":"numpy.ndarray"},{".class":"Instance","args":[{".class":"Instance","args":[{".class":"AnyType","missing_import_name":null,"source_any":null,"type_of_any":6}],"extra_attrs":null,"type_ref":"builtins.tuple"},{".class":"Instance","args":[{".class":"AnyType","missing_import_name":null,"source_any":null,"type_of_any":2}],"extra_attrs":null,"type_ref":"numpy.dtype"}],"extra_attrs":null,"type_ref":"numpy.ndarray"},{".class":"Instance","args":[{".class":"Instance","args":[{".class":"AnyType","missing_import_name":null,"source_any":null,"type_of_any":6}],"extra_attrs":null,"type_ref":"builtins.tuple"},{".class":"Instance","args":[{".class":"AnyType","missing_import_name":null,"source_any":null,"type_of_any":2}],"extra_attrs":null,"type_ref":"numpy.dtype"}],"extra_attrs":null,"type_ref":"numpy.ndarray"},{".class":"Instance","args":[{".class":"Instance","args":[{".class":"AnyType","missing_import_name":null,"source_any":null,"type_of_any":6}],"extra_attrs":null,"type_ref":"builtins.tuple"},{".class":"Instance","args":[{".class":"AnyType","missing_import_name":null,"source_any":null,"type_of_any":2}],"extra_attrs":null,"type_ref":"numpy.dtype"}],"extra_attrs":null,"type_ref":"numpy.ndarray"},{".class":"Instance","args":[{".class":"Instance","args":[{".class":"AnyType","missing_import_name":null,"source_any":null,"type_of_any":6}],"extra_attrs":null,"type_ref":"builtins.tuple"},{".class":"Instance","args":[{".class":"AnyType","missing_import_name":null,"source_any":null,"type_of_any":2}],"extra_attrs":null,"type_ref":"numpy.dtype"}],"extra_attrs":null,"type_ref":"numpy.ndarray"},"builtins.int"],"bound_args":[],"def_extras":{"first_arg":"self"},"fallback":"builtins.function","from_concatenate":false,"implicit":false,"imprecise_arg_kinds":false,"is_ellipsis_args":false,"name":"_step of CommonLSTM","ret_type":{".class":"TupleType","implicit":false,"items":[{".class":"Instance","args":[{".class":"Instance","args":[{".class":"AnyType","missing_import_name":null,"source_any":null,"type_of_any":6}],"extra_attrs":null,"type_ref":"builtins.tuple"},{".class":"Instance","args":[{".class":"AnyType","missing_import_name":null,"source_any":null,"type_of_any":2}],"extra_attrs":null,"type_ref":"numpy.dtype"}],"extra_attrs":null,"type_ref":"numpy.ndarray"},{".class":"Instance","args":[{".class":"Instance","args":[{".class":"AnyType","missing_import_name":null,"source_any":null,"type_of_any":6}],"extra_attrs":null,"type_ref":"builtins.tuple"},{".class":"Instance","args":[{".class":"AnyType","missing_import_name":null,"source_any":null,"type_of_any":2}],"extra_attrs":null,"type_ref":"numpy.dtype"}],"extra_attrs":null,"type_ref":"numpy.ndarray"}],"partial_fallback":{".class":"Instance","args":[{".class":"AnyType","missing_import_name":null,"source_any":null,"type_of_any":6}],"extra_attrs":null,"type_ref":"builtins.tuple"}},"type_guard":null,"type_is":null,"unpack_kwargs":false,"variables":[]}}},"f":{".class":"SymbolTableNode","kind":"Mdef","node":{".class":"FuncDef","abstract_status":0,"arg_kinds":[0,0],"arg_names":["self","x"],"dataclass_transform_spec":null,"deprecated":null,"flags":[],"fullname":"onnx.reference.ops.op_lstm.CommonLSTM.f","name":"f","type":{".class":"CallableType","arg_kinds":[0,0],"arg_names":["self","x"],"arg_types":["onnx.reference.ops.op_lstm.CommonLSTM",{".class":"Instance","args":[{".class":"Instance","args":[{".class":"AnyType","missing_import_name":null,"source_any":null,"type_of_any":6}],"extra_attrs":null,"type_ref":"builtins.tuple"},{".class":"Instance","args":[{".class":"AnyType","missing_import_name":null,"source_any":null,"type_of_any":2}],"extra_attrs":null,"type_ref":"numpy.dtype"}],"extra_attrs":null,"type_ref":"numpy.ndarray"}],"bound_args":[],"def_extras":{"first_arg":"self"},"fallback":"builtins.function","from_concatenate":false,"implicit":false,"imprecise_arg_kinds":false,"is_ellipsis_args":false,"name":"f of CommonLSTM","ret_type":{".class":"Instance","args":[{".class":"Instance","args":[{".class":"AnyType","missing_import_name":null,"source_any":null,"type_of_any":6}],"extra_attrs":null,"type_ref":"builtins.tuple"},{".class":"Instance","args":[{".class":"AnyType","missing_import_name":null,"source_any":null,"type_of_any":2}],"extra_attrs":null,"type_ref":"numpy.dtype"}],"extra_attrs":null,"type_ref":"numpy.ndarray"},"type_guard":null,"type_is":null,"unpack_kwargs":false,"variables":[]}}},"g":{".class":"SymbolTableNode","kind":"Mdef","node":{".class":"FuncDef","abstract_status":0,"arg_kinds":[0,0],"arg_names":["self","x"],"dataclass_transform_spec":null,"deprecated":null,"flags":[],"fullname":"onnx.reference.ops.op_lstm.CommonLSTM.g","name":"g","type":{".class":"CallableType","arg_kinds":[0,0],"arg_names":["self","x"],"arg_types":["onnx.reference.ops.op_lstm.CommonLSTM",{".class":"Instance","args":[{".class":"Instance","args":[{".class":"AnyType","missing_import_name":null,"source_any":null,"type_of_any":6}],"extra_attrs":null,"type_ref":"builtins.tuple"},{".class":"Instance","args":[{".class":"AnyType","missing_import_name":null,"source_any":null,"type_of_any":2}],"extra_attrs":null,"type_ref":"numpy.dtype"}],"extra_attrs":null,"type_ref":"numpy.ndarray"}],"bound_args":[],"def_extras":{"first_arg":"self"},"fallback":"builtins.function","from_concatenate":false,"implicit":false,"imprecise_arg_kinds":false,"is_ellipsis_args":false,"name":"g of CommonLSTM","ret_type":{".class":"Instance","args":[{".class":"Instance","args":[{".class":"AnyType","missing_import_name":null,"source_any":null,"type_of_any":6}],"extra_attrs":null,"type_ref":"builtins.tuple"},{".class":"Instance","args":[{".class":"AnyType","missing_import_name":null,"source_any":null,"type_of_any":2}],"extra_attrs":null,"type_ref":"numpy.dtype"}],"extra_attrs":null,"type_ref":"numpy.ndarray"},"type_guard":null,"type_is":null,"unpack_kwargs":false,"variables":[]}}},"h":{".class":"SymbolTableNode","kind":"Mdef","node":{".class":"FuncDef","abstract_status":0,"arg_kinds":[0,0],"arg_names":["self","x"],"dataclass_transform_spec":null,"deprecated":null,"flags":[],"fullname":"onnx.reference.ops.op_lstm.CommonLSTM.h","name":"h","type":{".class":"CallableType","arg_kinds":[0,0],"arg_names":["self","x"],"arg_types":["onnx.reference.ops.op_lstm.CommonLSTM",{".class":"Instance","args":[{".class":"Instance","args":[{".class":"AnyType","missing_import_name":null,"source_any":null,"type_of_any":6}],"extra_attrs":null,"type_ref":"builtins.tuple"},{".class":"Instance","args":[{".class":"AnyType","missing_import_name":null,"source_any":null,"type_of_any":2}],"extra_attrs":null,"type_ref":"numpy.dtype"}],"extra_attrs":null,"type_ref":"numpy.ndarray"}],"bound_args":[],"def_extras":{"first_arg":"self"},"fallback":"builtins.function","from_concatenate":false,"implicit":false,"imprecise_arg_kinds":false,"is_ellipsis_args":false,"name":"h of CommonLSTM","ret_type":{".class":"Instance","args":[{".class":"Instance","args":[{".class":"AnyType","missing_import_name":null,"source_any":null,"type_of_any":6}],"extra_attrs":null,"type_ref":"builtins.tuple"},{".class":"Instance","args":[{".class":"AnyType","missing_import_name":null,"source_any":null,"type_of_any":2}],"extra_attrs":null,"type_ref":"numpy.dtype"}],"extra_attrs":null,"type_ref":"numpy.ndarray"},"type_guard":null,"type_is":null,"unpack_kwargs":false,"variables":[]}}},"n_gates":{".class":"SymbolTableNode","implicit":true,"kind":"Mdef","node":{".class":"Var","flags":["is_inferred"],"fullname":"onnx.reference.ops.op_lstm.CommonLSTM.n_gates","name":"n_gates","type":"builtins.int"}},"n_outputs":{".class":"SymbolTableNode","implicit":true,"kind":"Mdef","node":{".class":"Var","flags":["is_inferred"],"fullname":"onnx.reference.ops.op_lstm.CommonLSTM.n_outputs","name":"n_outputs","type":"builtins.int"}}},"self_type":{".class":"TypeVarType","default":{".class":"AnyType","missing_import_name":null,"source_any":null,"type_of_any":4},"fullname":"onnx.reference.ops.op_lstm.CommonLSTM.Self","id":0,"name":"Self","namespace":"","upper_bound":"onnx.reference.ops.op_lstm.CommonLSTM","values":[],"variance":0},"slots":null,"tuple_type":null,"type_vars":[],"typeddict_type":null}},"LSTM":{".class":"SymbolTableNode","kind":"Gdef","node":{".class":"TypeInfo","_promote":[],"abstract_attributes":[],"alt_promote":null,"bases":["onnx.reference.ops.op_lstm.CommonLSTM"],"dataclass_transform_spec":null,"declared_metaclass":null,"defn":{".class":"ClassDef","fullname":"onnx.reference.ops.op_lstm.LSTM","name":"LSTM","type_vars":[]},"deletable_attributes":[],"deprecated":null,"flags":[],"fullname":"onnx.reference.ops.op_lstm.LSTM","has_param_spec_type":false,"metaclass_type":"abc.ABCMeta","metadata":{},"module_name":"onnx.reference.ops.op_lstm","mro":["onnx.reference.ops.op_lstm.LSTM","onnx.reference.ops.op_lstm.CommonLSTM","onnx.reference.op_run.OpRun","abc.ABC","builtins.object"],"names":{".class":"SymbolTable","__init__":{".class":"SymbolTableNode","kind":"Mdef","node":{".class":"FuncDef","abstract_status":0,"arg_kinds":[0,0,0],"arg_names":["self","onnx_node","run_params"],"dataclass_transform_spec":null,"deprecated":null,"flags":[],"fullname":"onnx.reference.ops.op_lstm.LSTM.__init__","name":"__init__","type":null}}},"self_type":{".class":"TypeVarType","default":{".class":"AnyType","missing_import_name":null,"source_any":null,"type_of_any":4},"fullname":"onnx.reference.ops.op_lstm.LSTM.Self","id":0,"name":"Self","namespace":"","upper_bound":"onnx.reference.ops.op_lstm.LSTM","values":[],"variance":0},"slots":null,"tuple_type":null,"type_vars":[],"typeddict_type":null}},"OpRun":{".class":"SymbolTableNode","cross_ref":"onnx.reference.op_run.OpRun","kind":"Gdef","module_hidden":true,"module_public":false},"__annotations__":{".class":"SymbolTableNode","kind":"Gdef","node":{".class":"Var","flags":["is_ready"],"fullname":"onnx.reference.ops.op_lstm.__annotations__","name":"__annotations__","type":{".class":"Instance","args":["builtins.str",{".class":"AnyType","missing_import_name":null,"source_any":null,"type_of_any":6}],"extra_attrs":null,"type_ref":"builtins.dict"}}},"__doc__":{".class":"SymbolTableNode","kind":"Gdef","node":{".class":"Var","flags":["is_ready"],"fullname":"onnx.reference.ops.op_lstm.__doc__","name":"__doc__","type":"builtins.str"}},"__file__":{".class":"SymbolTableNode","kind":"Gdef","node":{".class":"Var","flags":["is_ready"],"fullname":"onnx.reference.ops.op_lstm.__file__","name":"__file__","type":"builtins.str"}},"__name__":{".class":"SymbolTableNode","kind":"Gdef","node":{".class":"Var","flags":["is_ready"],"fullname":"onnx.reference.ops.op_lstm.__name__","name":"__name__","type":"builtins.str"}},"__package__":{".class":"SymbolTableNode","kind":"Gdef","node":{".class":"Var","flags":["is_ready"],"fullname":"onnx.reference.ops.op_lstm.__package__","name":"__package__","type":"builtins.str"}},"__spec__":{".class":"SymbolTableNode","kind":"Gdef","node":{".class":"Var","flags":["is_ready"],"fullname":"onnx.reference.ops.op_lstm.__spec__","name":"__spec__","type":"_frozen_importlib.ModuleSpec"}},"annotations":{".class":"SymbolTableNode","cross_ref":"__future__.annotations","kind":"Gdef","module_hidden":true,"module_public":false},"np":{".class":"SymbolTableNode","cross_ref":"numpy","kind":"Gdef","module_hidden":true,"module_public":false}},"path":"C:\\Users\\yunus\\AppData\\Local\\Python\\pythoncore-3.14-64\\Lib\\site-packages\\onnx\\reference\\ops\\op_lstm.py"}